ndjson_testrunner/__init__.py
ndjson_testrunner/__main__.py
ndjson_testrunner/py.typed
ndjson_testrunner-1.1.3.dist-info/METADATA
ndjson_testrunner-1.1.3.dist-info/WHEEL
ndjson_testrunner-1.1.3.dist-info/licenses/LICENSE
ndjson_testrunner-1.1.3.dist-info/RECORD
