Metadata-Version: 2.3
Name: ndjson-testrunner
Version: 1.1.3
Summary: A test runner that outputs newline delimited JSON results
Project-URL: Source, https://github.com/flying-sheep/ndjson-testrunner
Author-email: "Philipp A." <flying-sheep@web.de>
License-Expression: GPL-3.0-or-later
License-File: LICENSE
Classifier: Intended Audience :: Developers
Classifier: Programming Language :: Python :: 3
Classifier: Programming Language :: Python :: 3.9
Classifier: Programming Language :: Python :: 3.10
Classifier: Programming Language :: Python :: 3.11
Classifier: Programming Language :: Python :: 3.12
Classifier: Topic :: Software Development :: Libraries
Classifier: Topic :: Software Development :: Testing
Classifier: Typing :: Typed
Requires-Python: >=3.9
